<?xml version="1.0" encoding="UTF-8"?>
<?xml-stylesheet href="/xml/XSLT/panelfile-4-19-2.xsl" type="text/xsl"?>
<layout-config xmlns:xsi="http://www.w3.org/2001/XMLSchema-instance" xsi:noNamespaceSchemaLocation="http://jmri.org/xml/schema/layout-4-19-2.xsd">
  <jmriversion>
    <major>4</major>
    <minor>19</minor>
    <test>2</test>
    <modifier />
  </jmriversion>
  <sensors class="jmri.jmrix.lenz.configurexml.XNetSensorManagerXml">
    <sensor inverted="false">
      <systemName>XS514</systemName>
    </sensor>
    <sensor inverted="false">
      <systemName>XS515</systemName>
    </sensor>
    <sensor inverted="false">
      <systemName>XS516</systemName>
    </sensor>
    <sensor inverted="false">
      <systemName>XS517</systemName>
    </sensor>
    <sensor inverted="false">
      <systemName>XS518</systemName>
    </sensor>
    <sensor inverted="false">
      <systemName>XS519</systemName>
    </sensor>
    <sensor inverted="false">
      <systemName>XS520</systemName>
    </sensor>
    <sensor inverted="false">
      <systemName>XS521</systemName>
    </sensor>
    <sensor inverted="false">
      <systemName>XS522</systemName>
    </sensor>
    <sensor inverted="false">
      <systemName>XS523</systemName>
    </sensor>
    <sensor inverted="false">
      <systemName>XS524</systemName>
    </sensor>
    <sensor inverted="false">
      <systemName>XS525</systemName>
    </sensor>
    <sensor inverted="false">
      <systemName>XS526</systemName>
    </sensor>
    <sensor inverted="false">
      <systemName>XS527</systemName>
    </sensor>
    <sensor inverted="false">
      <systemName>XS528</systemName>
    </sensor>
    <sensor inverted="false">
      <systemName>XS529</systemName>
    </sensor>
    <sensor inverted="false">
      <systemName>XS530</systemName>
    </sensor>
    <sensor inverted="false">
      <systemName>XS531</systemName>
    </sensor>
    <sensor inverted="false">
      <systemName>XS532</systemName>
    </sensor>
    <sensor inverted="false">
      <systemName>XS537</systemName>
    </sensor>
    <sensor inverted="false">
      <systemName>XS538</systemName>
    </sensor>
    <sensor inverted="false">
      <systemName>XS539</systemName>
    </sensor>
    <sensor inverted="false">
      <systemName>XS540</systemName>
    </sensor>
    <sensor inverted="false">
      <systemName>XS541</systemName>
    </sensor>
    <sensor inverted="false">
      <systemName>XS542</systemName>
    </sensor>
  </sensors>
  <sensors class="jmri.jmrix.cmri.serial.configurexml.SerialSensorManagerXml">
    <sensor inverted="false">
      <systemName>CS1001</systemName>
    </sensor>
    <sensor inverted="false">
      <systemName>CS1002</systemName>
    </sensor>
    <sensor inverted="false">
      <systemName>CS1003</systemName>
    </sensor>
    <sensor inverted="false">
      <systemName>CS1004</systemName>
    </sensor>
    <sensor inverted="false">
      <systemName>CS1005</systemName>
    </sensor>
    <sensor inverted="false">
      <systemName>CS1006</systemName>
    </sensor>
    <sensor inverted="false">
      <systemName>CS1007</systemName>
    </sensor>
    <sensor inverted="false">
      <systemName>CS2001</systemName>
    </sensor>
    <sensor inverted="false">
      <systemName>CS2002</systemName>
    </sensor>
    <sensor inverted="false">
      <systemName>CS2003</systemName>
    </sensor>
    <sensor inverted="false">
      <systemName>CS2004</systemName>
    </sensor>
  </sensors>
  <turnouts class="jmri.jmrix.lenz.configurexml.XNetTurnoutManagerXml">
    <operations automate="false">
      <operation name="NoFeedback" class="jmri.configurexml.turnoutoperations.NoFeedbackTurnoutOperationXml" interval="300" maxtries="2" />
      <operation name="Raw" class="jmri.configurexml.turnoutoperations.RawTurnoutOperationXml" interval="300" maxtries="1" />
      <operation name="Sensor" class="jmri.configurexml.turnoutoperations.SensorTurnoutOperationXml" interval="300" maxtries="3" />
    </operations>
    <defaultclosedspeed>Normal</defaultclosedspeed>
    <defaultthrownspeed>Restricted</defaultthrownspeed>
    <turnout feedback="MONITORING" inverted="false" automate="Off">
      <systemName>XT1</systemName>
    </turnout>
    <turnout feedback="MONITORING" inverted="false" automate="Off">
      <systemName>XT2</systemName>
    </turnout>
    <turnout feedback="MONITORING" inverted="false" automate="Off">
      <systemName>XT3</systemName>
    </turnout>
    <turnout feedback="MONITORING" inverted="false" automate="Off">
      <systemName>XT5</systemName>
    </turnout>
    <turnout feedback="MONITORING" inverted="false" automate="Off">
      <systemName>XT6</systemName>
    </turnout>
    <turnout feedback="MONITORING" inverted="false" automate="Off">
      <systemName>XT9</systemName>
    </turnout>
    <turnout feedback="MONITORING" inverted="false" automate="Off">
      <systemName>XT13</systemName>
    </turnout>
    <turnout feedback="MONITORING" inverted="false" automate="Off">
      <systemName>XT14</systemName>
    </turnout>
    <turnout feedback="MONITORING" inverted="false" automate="Off">
      <systemName>XT17</systemName>
    </turnout>
    <turnout feedback="MONITORING" inverted="false" automate="Off">
      <systemName>XT18</systemName>
    </turnout>
    <turnout feedback="MONITORING" inverted="false" automate="Off">
      <systemName>XT19</systemName>
    </turnout>
    <turnout feedback="MONITORING" inverted="false" automate="Off">
      <systemName>XT21</systemName>
    </turnout>
    <turnout feedback="MONITORING" inverted="false" automate="Off">
      <systemName>XT22</systemName>
    </turnout>
    <turnout feedback="MONITORING" inverted="false" automate="Off">
      <systemName>XT25</systemName>
    </turnout>
    <turnout feedback="MONITORING" inverted="false" automate="Off">
      <systemName>XT26</systemName>
    </turnout>
    <turnout feedback="MONITORING" inverted="false" automate="Off">
      <systemName>XT27</systemName>
    </turnout>
    <turnout feedback="MONITORING" inverted="false" automate="Off">
      <systemName>XT28</systemName>
    </turnout>
    <turnout feedback="MONITORING" inverted="false" automate="Off">
      <systemName>XT29</systemName>
    </turnout>
    <turnout feedback="MONITORING" inverted="false" automate="Off">
      <systemName>XT30</systemName>
    </turnout>
    <turnout feedback="MONITORING" inverted="false" automate="Off">
      <systemName>XT31</systemName>
    </turnout>
    <turnout feedback="MONITORING" inverted="false" automate="Off">
      <systemName>XT32</systemName>
    </turnout>
    <turnout feedback="MONITORING" inverted="false" automate="Off">
      <systemName>XT33</systemName>
    </turnout>
    <turnout feedback="MONITORING" inverted="false" automate="Off">
      <systemName>XT34</systemName>
    </turnout>
    <turnout feedback="MONITORING" inverted="false" automate="Off">
      <systemName>XT35</systemName>
    </turnout>
    <turnout feedback="MONITORING" inverted="false" automate="Off">
      <systemName>XT36</systemName>
    </turnout>
    <turnout feedback="MONITORING" inverted="false" automate="Off">
      <systemName>XT37</systemName>
    </turnout>
    <turnout feedback="MONITORING" inverted="false" automate="Off">
      <systemName>XT38</systemName>
    </turnout>
    <turnout feedback="MONITORING" inverted="false" automate="Off">
      <systemName>XT39</systemName>
    </turnout>
    <turnout feedback="MONITORING" inverted="false" automate="Off">
      <systemName>XT41</systemName>
    </turnout>
    <turnout feedback="MONITORING" inverted="false" automate="Off">
      <systemName>XT42</systemName>
    </turnout>
    <turnout feedback="MONITORING" inverted="false" automate="Off">
      <systemName>XT43</systemName>
    </turnout>
    <turnout feedback="MONITORING" inverted="false" automate="Off">
      <systemName>XT44</systemName>
    </turnout>
    <turnout feedback="MONITORING" inverted="false" automate="Off">
      <systemName>XT45</systemName>
    </turnout>
    <turnout feedback="MONITORING" inverted="false" automate="Off">
      <systemName>XT46</systemName>
    </turnout>
    <turnout feedback="MONITORING" inverted="false" automate="Off">
      <systemName>XT47</systemName>
    </turnout>
    <turnout feedback="MONITORING" inverted="false" automate="Off">
      <systemName>XT48</systemName>
    </turnout>
    <turnout feedback="MONITORING" inverted="false" automate="Off">
      <systemName>XT49</systemName>
    </turnout>
    <turnout feedback="MONITORING" inverted="false" automate="Off">
      <systemName>XT50</systemName>
    </turnout>
    <turnout feedback="MONITORING" inverted="false" automate="Off">
      <systemName>XT51</systemName>
    </turnout>
    <turnout feedback="MONITORING" inverted="false" automate="Off">
      <systemName>XT52</systemName>
    </turnout>
    <turnout feedback="MONITORING" inverted="false" automate="Off">
      <systemName>XT53</systemName>
    </turnout>
    <turnout feedback="MONITORING" inverted="false" automate="Off">
      <systemName>XT54</systemName>
    </turnout>
    <turnout feedback="MONITORING" inverted="false" automate="Off">
      <systemName>XT55</systemName>
    </turnout>
    <turnout feedback="MONITORING" inverted="false" automate="Off">
      <systemName>XT57</systemName>
    </turnout>
    <turnout feedback="MONITORING" inverted="false" automate="Off">
      <systemName>XT58</systemName>
    </turnout>
    <turnout feedback="MONITORING" inverted="false" automate="Off">
      <systemName>XT61</systemName>
    </turnout>
    <turnout feedback="MONITORING" inverted="false" automate="Off">
      <systemName>XT62</systemName>
    </turnout>
  </turnouts>
  <turnouts class="jmri.jmrix.cmri.serial.configurexml.SerialTurnoutManagerXml">
    <operations automate="false">
      <operation name="NoFeedback" class="jmri.configurexml.turnoutoperations.NoFeedbackTurnoutOperationXml" interval="300" maxtries="2" />
      <operation name="Raw" class="jmri.configurexml.turnoutoperations.RawTurnoutOperationXml" interval="300" maxtries="1" />
      <operation name="Sensor" class="jmri.configurexml.turnoutoperations.SensorTurnoutOperationXml" interval="300" maxtries="3" />
    </operations>
    <defaultclosedspeed>Normal</defaultclosedspeed>
    <defaultthrownspeed>Restricted</defaultthrownspeed>
    <turnout feedback="DIRECT" inverted="false" automate="Off">
      <systemName>CT1001</systemName>
    </turnout>
    <turnout feedback="DIRECT" inverted="false" automate="Off">
      <systemName>CT1002</systemName>
    </turnout>
    <turnout feedback="DIRECT" inverted="false" automate="Off">
      <systemName>CT1003</systemName>
    </turnout>
    <turnout feedback="DIRECT" inverted="false" automate="Off">
      <systemName>CT1004</systemName>
    </turnout>
    <turnout feedback="DIRECT" inverted="false" automate="Off">
      <systemName>CT1005</systemName>
    </turnout>
    <turnout feedback="DIRECT" inverted="false" automate="Off">
      <systemName>CT1006</systemName>
    </turnout>
    <turnout feedback="DIRECT" inverted="false" automate="Off">
      <systemName>CT1007</systemName>
    </turnout>
    <turnout feedback="DIRECT" inverted="false" automate="Off">
      <systemName>CT1008</systemName>
    </turnout>
    <turnout feedback="DIRECT" inverted="false" automate="Off">
      <systemName>CT1009</systemName>
    </turnout>
    <turnout feedback="DIRECT" inverted="false" automate="Off">
      <systemName>CT1010</systemName>
    </turnout>
    <turnout feedback="DIRECT" inverted="false" automate="Off">
      <systemName>CT1011</systemName>
    </turnout>
    <turnout feedback="DIRECT" inverted="false" automate="Off">
      <systemName>CT1012</systemName>
    </turnout>
    <turnout feedback="DIRECT" inverted="false" automate="Off">
      <systemName>CT1013</systemName>
    </turnout>
    <turnout feedback="DIRECT" inverted="false" automate="Off">
      <systemName>CT1014</systemName>
    </turnout>
    <turnout feedback="DIRECT" inverted="false" automate="Off">
      <systemName>CT1015</systemName>
    </turnout>
    <turnout feedback="DIRECT" inverted="false" automate="Off">
      <systemName>CT1016</systemName>
    </turnout>
    <turnout feedback="DIRECT" inverted="false" automate="Off">
      <systemName>CT1017</systemName>
    </turnout>
    <turnout feedback="DIRECT" inverted="false" automate="Off">
      <systemName>CT1018</systemName>
    </turnout>
    <turnout feedback="DIRECT" inverted="false" automate="Off">
      <systemName>CT1019</systemName>
    </turnout>
    <turnout feedback="DIRECT" inverted="false" automate="Off">
      <systemName>CT1020</systemName>
    </turnout>
    <turnout feedback="DIRECT" inverted="false" automate="Off">
      <systemName>CT1021</systemName>
    </turnout>
    <turnout feedback="DIRECT" inverted="false" automate="Off">
      <systemName>CT1022</systemName>
    </turnout>
    <turnout feedback="DIRECT" inverted="false" automate="Off">
      <systemName>CT1023</systemName>
    </turnout>
    <turnout feedback="DIRECT" inverted="false" automate="Off">
      <systemName>CT1024</systemName>
    </turnout>
    <turnout feedback="DIRECT" inverted="false" automate="Off">
      <systemName>CT1025</systemName>
    </turnout>
    <turnout feedback="DIRECT" inverted="false" automate="Off">
      <systemName>CT1026</systemName>
    </turnout>
    <turnout feedback="DIRECT" inverted="false" automate="Off">
      <systemName>CT1027</systemName>
    </turnout>
    <turnout feedback="DIRECT" inverted="false" automate="Off">
      <systemName>CT1028</systemName>
    </turnout>
    <turnout feedback="DIRECT" inverted="false" automate="Off">
      <systemName>CT1029</systemName>
    </turnout>
    <turnout feedback="DIRECT" inverted="false" automate="Off">
      <systemName>CT1030</systemName>
    </turnout>
    <turnout feedback="DIRECT" inverted="false" automate="Off">
      <systemName>CT1031</systemName>
    </turnout>
    <turnout feedback="DIRECT" inverted="false" automate="Off">
      <systemName>CT1032</systemName>
    </turnout>
    <turnout feedback="DIRECT" inverted="false" automate="Off">
      <systemName>CT1033</systemName>
    </turnout>
    <turnout feedback="DIRECT" inverted="false" automate="Off">
      <systemName>CT1034</systemName>
    </turnout>
    <turnout feedback="DIRECT" inverted="false" automate="Off">
      <systemName>CT1035</systemName>
    </turnout>
    <turnout feedback="DIRECT" inverted="false" automate="Off">
      <systemName>CT1036</systemName>
    </turnout>
    <turnout feedback="DIRECT" inverted="false" automate="Off">
      <systemName>CT1037</systemName>
    </turnout>
    <turnout feedback="DIRECT" inverted="false" automate="Off">
      <systemName>CT1038</systemName>
    </turnout>
    <turnout feedback="DIRECT" inverted="false" automate="Off">
      <systemName>CT1039</systemName>
    </turnout>
    <turnout feedback="DIRECT" inverted="false" automate="Off">
      <systemName>CT1040</systemName>
    </turnout>
    <turnout feedback="DIRECT" inverted="false" automate="Off">
      <systemName>CT1041</systemName>
    </turnout>
    <turnout feedback="DIRECT" inverted="false" automate="Off">
      <systemName>CT1042</systemName>
    </turnout>
    <turnout feedback="DIRECT" inverted="false" automate="Off">
      <systemName>CT1043</systemName>
    </turnout>
    <turnout feedback="DIRECT" inverted="false" automate="Off">
      <systemName>CT1044</systemName>
    </turnout>
    <turnout feedback="DIRECT" inverted="false" automate="Off">
      <systemName>CT1045</systemName>
    </turnout>
    <turnout feedback="DIRECT" inverted="false" automate="Off">
      <systemName>CT1046</systemName>
    </turnout>
    <turnout feedback="DIRECT" inverted="false" automate="Off">
      <systemName>CT1047</systemName>
    </turnout>
    <turnout feedback="DIRECT" inverted="false" automate="Off">
      <systemName>CT1048</systemName>
    </turnout>
    <turnout feedback="DIRECT" inverted="false" automate="Off">
      <systemName>CT2001</systemName>
    </turnout>
    <turnout feedback="DIRECT" inverted="false" automate="Off">
      <systemName>CT2002</systemName>
    </turnout>
    <turnout feedback="DIRECT" inverted="false" automate="Off">
      <systemName>CT2003</systemName>
    </turnout>
    <turnout feedback="DIRECT" inverted="false" automate="Off">
      <systemName>CT2004</systemName>
    </turnout>
    <turnout feedback="DIRECT" inverted="false" automate="Off">
      <systemName>CT2005</systemName>
    </turnout>
    <turnout feedback="DIRECT" inverted="false" automate="Off">
      <systemName>CT2006</systemName>
    </turnout>
    <turnout feedback="DIRECT" inverted="false" automate="Off">
      <systemName>CT2007</systemName>
    </turnout>
    <turnout feedback="DIRECT" inverted="false" automate="Off">
      <systemName>CT2008</systemName>
    </turnout>
    <turnout feedback="DIRECT" inverted="false" automate="Off">
      <systemName>CT2009</systemName>
    </turnout>
    <turnout feedback="DIRECT" inverted="false" automate="Off">
      <systemName>CT2010</systemName>
    </turnout>
    <turnout feedback="DIRECT" inverted="false" automate="Off">
      <systemName>CT2011</systemName>
    </turnout>
    <turnout feedback="DIRECT" inverted="false" automate="Off">
      <systemName>CT2012</systemName>
    </turnout>
    <turnout feedback="DIRECT" inverted="false" automate="Off">
      <systemName>CT2013</systemName>
    </turnout>
    <turnout feedback="DIRECT" inverted="false" automate="Off">
      <systemName>CT2014</systemName>
    </turnout>
    <turnout feedback="DIRECT" inverted="false" automate="Off">
      <systemName>CT2015</systemName>
    </turnout>
    <turnout feedback="DIRECT" inverted="false" automate="Off">
      <systemName>CT2016</systemName>
    </turnout>
    <turnout feedback="DIRECT" inverted="false" automate="Off">
      <systemName>CT2017</systemName>
    </turnout>
    <turnout feedback="DIRECT" inverted="false" automate="Off">
      <systemName>CT2018</systemName>
    </turnout>
    <turnout feedback="DIRECT" inverted="false" automate="Off">
      <systemName>CT2019</systemName>
    </turnout>
    <turnout feedback="DIRECT" inverted="false" automate="Off">
      <systemName>CT2020</systemName>
    </turnout>
    <turnout feedback="DIRECT" inverted="false" automate="Off">
      <systemName>CT2021</systemName>
    </turnout>
    <turnout feedback="DIRECT" inverted="false" automate="Off">
      <systemName>CT2022</systemName>
    </turnout>
    <turnout feedback="DIRECT" inverted="false" automate="Off">
      <systemName>CT2023</systemName>
    </turnout>
    <turnout feedback="DIRECT" inverted="false" automate="Off">
      <systemName>CT2024</systemName>
    </turnout>
    <turnout feedback="DIRECT" inverted="false" automate="Off">
      <systemName>CT2025</systemName>
    </turnout>
    <turnout feedback="DIRECT" inverted="false" automate="Off">
      <systemName>CT2026</systemName>
    </turnout>
    <turnout feedback="DIRECT" inverted="false" automate="Off">
      <systemName>CT2027</systemName>
    </turnout>
    <turnout feedback="DIRECT" inverted="false" automate="Off">
      <systemName>CT2028</systemName>
    </turnout>
    <turnout feedback="DIRECT" inverted="false" automate="Off">
      <systemName>CT2029</systemName>
    </turnout>
    <turnout feedback="DIRECT" inverted="false" automate="Off">
      <systemName>CT2030</systemName>
    </turnout>
    <turnout feedback="DIRECT" inverted="false" automate="Off">
      <systemName>CT2031</systemName>
    </turnout>
    <turnout feedback="DIRECT" inverted="false" automate="Off">
      <systemName>CT2032</systemName>
    </turnout>
    <turnout feedback="DIRECT" inverted="false" automate="Off">
      <systemName>CT2033</systemName>
    </turnout>
    <turnout feedback="DIRECT" inverted="false" automate="Off">
      <systemName>CT2034</systemName>
    </turnout>
    <turnout feedback="DIRECT" inverted="false" automate="Off">
      <systemName>CT2035</systemName>
    </turnout>
    <turnout feedback="DIRECT" inverted="false" automate="Off">
      <systemName>CT2036</systemName>
    </turnout>
    <turnout feedback="DIRECT" inverted="false" automate="Off">
      <systemName>CT2037</systemName>
    </turnout>
    <turnout feedback="DIRECT" inverted="false" automate="Off">
      <systemName>CT2038</systemName>
    </turnout>
    <turnout feedback="DIRECT" inverted="false" automate="Off">
      <systemName>CT2039</systemName>
    </turnout>
    <turnout feedback="DIRECT" inverted="false" automate="Off">
      <systemName>CT2040</systemName>
    </turnout>
    <turnout feedback="DIRECT" inverted="false" automate="Off">
      <systemName>CT2041</systemName>
    </turnout>
    <turnout feedback="DIRECT" inverted="false" automate="Off">
      <systemName>CT2042</systemName>
    </turnout>
  </turnouts>
  <signalmastlogics class="jmri.managers.configurexml.DefaultSignalMastLogicManagerXml">
    <logicDelay>500</logicDelay>
  </signalmastlogics>
  <filehistory>
    <operation>
      <type>app</type>
      <date>Wed Jan 29 00:35:15 CST 2020</date>
      <filename>JMRI program</filename>
    </operation>
    <operation>
      <type>Store</type>
      <date>Wed Jan 29 06:30:15 CST 2020</date>
      <filename />
    </operation>
  </filehistory>
  <!--Written by JMRI version 4.19.2+R846b684 on Wed Jan 29 06:30:15 CST 2020-->
</layout-config>
